{
  "id": 9,
  "title": "Состояния процессов",
  "lessonContent": "Давайте еще раз посмотрим на команду ps aux:\n\n<pre>$ ps aux</pre>\n\nВ столбце STAT вы увидите много значений. Процесс в Linux может находиться в различных состояниях. Наиболее распространенные коды состояний, которые вы увидите, описаны ниже:\n\n<ul>\n<li>R: работает или готов к выполнению, просто ожидает, когда процессор начнет его обрабатывать</li>\n<li>S: прерываемый сон, ожидание завершения события, такого как ввод с терминала</li>\n<li>D: непрерываемый сон, процессы, которые нельзя убить или прервать сигналом, обычно для их завершения вам придется перезагрузить систему или устранить проблему</li>\n<li>Z: зомби, мы уже обсуждали в предыдущем уроке, что зомби - это завершенные процессы, ожидающие сбора своих статусов</li>\n<li>T: остановлен, процесс был приостановлен/остановлен</li>\n</ul>",
  "exercise": "Посмотрите на работающие процессы на вашей системе и изучите их состояния процессов.",
  "quizQuestion": "Какой код STAT используется для представления непрерываемого сна?",
  "quizAnswer": "D",
  "slug": "processstates"
}