{
  "id": 3,
  "title": "一般的なログ記録",
  "lessonContent": "システム上で表示できる多くのログファイルがあります。重要なものの多くは /var/log 以下にあります。全てを説明することはしませんが、いくつかの主要なログについては議論します。\n\nシステムの動作を一部把握するために表示できる一般的なログファイルが2つあります:\n\n<b>/var/log/messages</b>\n\nこのログには、非クリティカルで非デバッグメッセージが含まれており、ブートアップ時（dmesg）、認証、cron、デーモンなどのログが含まれています。マシンの動作を一部把握するのに非常に役立ちます。\n\n<b>/var/log/syslog</b>\n\nこのログは認証メッセージを除くすべてを記録し、マシン上のエラーのデバッグに非常に役立ちます。\n\nこれら2つのログは、システムの問題をトラブルシューティングする際には十分です。ただし、特定のログコンポーネントを表示したい場合は、それらのための個別のログもあります。",
  "exercise": "/var/log/messages と /var/log/syslog ファイルを見て、違いを確認してください。",
  "quizQuestion": "どのログファイルが認証メッセージを除くすべてを記録しますか？",
  "quizAnswer": "syslog",
  "slug": "generallogging"
}