{
  "id": 9,
  "title": "Arch Linux",
  "lessonContent": "<b>Vue d'ensemble</b>\nArch est une distribution Linux légère et flexible entièrement pilotée par la communauté. Similaire à Debian, Arch utilise un modèle de publication continue, de sorte que les mises à jour progressives finissent par devenir la version stable. Vous devez vraiment mettre les mains dans le cambouis pour comprendre le système et ses fonctions, mais en retour, vous obtenez un contrôle complet et total de votre système.\n\n<b>Gestion des paquets</b>\nIl utilise son propre gestionnaire de paquets, Pacman, pour installer, mettre à jour et gérer les paquets.\n\n<b>Configurabilité</b>\nSi vous voulez un système d'exploitation léger et vraiment comprendre Linux, utilisez Arch ! Il y a une courbe d'apprentissage, mais pour les utilisateurs de Linux chevronnés, c'est un excellent choix.\n\n<b>Utilisations</b>\nIdéal pour les ordinateurs de bureau et les ordinateurs portables. Si vous avez également un petit appareil tel qu'un Raspberry Pi et avez besoin d'y installer un système d'exploitation léger, vous ne pouvez pas vous tromper avec Arch.",
  "exercise": "Si vous êtes intéressé par l'utilisation d'Arch comme système d'exploitation, rendez-vous dans la section d'installation et essayez-le : <a href='https://www.archlinux.org/'>https://www.archlinux.org/</a>",
  "quizQuestion": "Quel gestionnaire de paquets utilise Arch Linux ?",
  "quizAnswer": "Pacman",
  "slug": "archlinux"
}