{
  "id": 1,
  "title": "/dev ディレクトリ",
  "lessonContent": "デバイスをマシンに接続するとき、通常、デバイスが正常に機能するためにはデバイスドライバが必要です。デバイスドライバとやり取りするには、デバイスファイルまたはデバイスノードを介します。これらは通常のファイルのように見える特別なファイルです。これらのデバイスファイルは通常、/dev ディレクトリに保存されています。システム上の /dev ディレクトリを ls してみてください。システムにある多くのデバイスファイルが表示されます。\n\n<pre>$ ls /dev </pre>\n\nこれらのデバイスのうち、/dev/null など、すでに使用してやり取りしたものがあります。/dev/null に出力を送信すると、カーネルはこのデバイスがすべての入力を受け取り、単に破棄することを知っているため、何も返されません。\n\n昔は、システムにデバイスを追加したい場合、/dev にデバイスファイルを追加してから、おそらくそれを忘れてしまうことがよくありました。これを何度も繰り返すと、問題が発生することがわかります。/dev ディレクトリは、長らく使用していないデバイスの静的なデバイスファイルでごったがえしてしまいます。デバイスは、カーネルがそれらを見つけた順番でデバイスファイルが割り当てられます。したがって、システムを再起動するたびに、デバイスは発見されたタイミングによって異なるデバイスファイルを持つ可能性があります。\n\n幸いなことに、もはやその方法は使用されておらず、現在は、システムで使用中のデバイスを動的に追加および削除するために使用するものがあり、これについては今後のレッスンで議論します。",
  "exercise": "/dev ディレクトリの内容を確認し、なじみのあるデバイスを認識できますか？",
  "quizQuestion": "システム上のデバイスファイルはどこに保存されていますか？",
  "quizAnswer": "/dev",
  "slug": "devdirectory"
}