{
  "id": 4,
  "title": "यूमास्क",
  "lessonContent": "हर फ़ाइल जो बनती है, उसके साथ एक डिफ़ॉल्ट सेट की अनुमतियाँ आती हैं। अगर आप इस डिफ़ॉल्ट सेट की अनुमतियों को बदलना चाहते हैं, तो आप यूमास्क कमांड के साथ ऐसा कर सकते हैं। यह कमांड उन 3 बिट अनुमति सेट को लेती है जो हम संख्यात्मक अनुमतियों में देखते हैं।\n\nइन अनुमतियों को जोड़ने की बजाय, यूमास्क इन अनुमतियों को हटा देती है।\n\n<pre>$ umask 021</pre>\n\nऊपर दिए गए उदाहरण में, हम कह रहे हैं कि हम नई फ़ाइलों की डिफ़ॉल्ट अनुमतियों को उन्हें पहुंचने की अनुमति देना चाहते हैं, लेकिन समूहों के लिए हम उनकी लेखन अनुमति को हटाना चाहते हैं और अन्य उपयोगकर्ताओं की लिए हम उनकी क्रियान्वित करने की अनुमति को हटाना चाहते हैं। अधिकांश वितरणों पर डिफ़ॉल्ट यूमास्क 022 है, जिसका मतलब है सभी उपयोगकर्ता पहुंच, लेकिन समूह और अन्य उपयोगकर्ताओं के लिए कोई लेखन पहुंच नहीं।\n\nजब आप यूमास्क कमांड चलाते हैं, तो वह उस डिफ़ॉल्ट सेट की अनुमतियों को किसी भी नई फ़ाइल पर देगा। हालांकि, अगर आप चाहते हैं कि यह बना रहे, तो आपको अपनी स्टार्टअप फ़ाइल को संशोधित करना होगा (.प्रोफ़ाइल), लेकिन हम उस पर बाद में चर्चा करेंगे।",
  "exercise": "<ol>\n<li>एक नई फ़ाइल बनाएं, फिर उसकी अनुमतियों का ध्यान रखें।</li>\n<li>यूमास्क को संशोधित करें और फिर एक और नई फ़ाइल बनाएं।</li>\n<li>नई फ़ाइल पर फिर से अनुमतियों की जाँच करें, आप क्या उम्मीद करते हैं देखने की?</li>\n<ol>",
  "quizQuestion": "डिफ़ॉल्ट फ़ाइल अनुमतियों को बदलने के लिए कौन सी कमांड उपयोग की जाती है?",
  "quizAnswer": "यूमास्क",
  "slug": "यूमास्क"
}